Workbook

Sheet 1_Parametros_y_Supuestos
A1: PARÁMETROS DE ENTRADA Y SUPUESTOS DEL MODELO FINANCIERO
A2: Proyecto: Automatización de Fin de Línea e Inspección Metrológica | Planta Láctea (Modelo Lácteos San Mateo)
A4: Categoría / Parámetro | B4: Valor | C4: Unidad | D4: Descripción / Fuente Técnica y Financiera
A5: PARÁMETROS MACROFINANCIEROS Y TRIBUTARIOS
A6: Tasa de Cambio Representativa (TRM) | B6: 3192.73 | C6: COP / USD | D6: Tasa de cambio base para nacionalización de hardware (Oct 2026)
A7: Horizonte de Evaluación | B7: 5 | C7: Años | D7: Período de proyección del flujo de caja libre operativo
A8: Tasa de Interés de Oportunidad (TIO / WACC) | B8: 0.135 | C8: % E.A. | D8: Costo promedio ponderado de capital sector lácteo en Colombia
A9: Impuesto sobre la Renta Corporativa | B9: 0.35 | C9: % | D9: Tarifa estatutaria vigente en Colombia
A10: Vida Útil de Depreciación Fiscal | B10: 5 | C10: Años | D10: Depreciación en línea recta sin valor residual contable intermedio
A11: Valor de Salvamento de Mercado (Año 5) | B11: 40000000 | C11: COP | D11: Valor de reposición conservador (~8,1% del activo inicial)
A12: PARÁMETROS OPERATIVOS Y DE CONSUMO ENERGÉTICO
A13: Días Laborales al Año | B13: =52*4 -> 208 | C13: días/año | D13: Régimen operativo de planta (4 días/semana)
A14: Horas por Turno Continuo | B14: 8 | C14: horas/día | D14: 1 turno diario de empaque y paletizado en cámara a 8°C
A15: Horas Operativas Anuales | B15: =B13*B14 -> 1664 | C15: horas/año | D15: Total de horas de operación efectiva al año
A16: Potencia Promedio - Robot Yaskawa PL80 | B16: 1.8 | C16: kW | D16: Consumo medio del manipulador de 4 ejes y controlador YRC1000
A17: Potencia Promedio - Compresor Atlas Copco | B17: 3.2 | C17: kW | D17: G 7P-10 FF ciclando bajo demanda de vacío de garra Schmalz
A18: Potencia Promedio - Rodillos e Indexadores | B18: 0.8 | C18: kW | D18: Transportador Interroll MDR 24V y actuadores neumáticos
A19: Potencia Promedio - Báscula y Visión | B19: 0.8 | C19: kW | D19: Checkweigher dinámico AISI 304L + cámara matricial IP67
A20: Potencia Total Demandada por la Celda | B20: =SUM(B16:B19) -> 6.6 | C20: kW | D20: Demanda eléctrica consolidada en operación continua
A21: Tarifa Media Industrial Regulada | B21: 850 | C21: COP / kWh | D21: Costo unitario de energía eléctrica industrial
A22: PARÁMETROS DE PRODUCCIÓN, METROLOGÍA Y NÓMINA
A23: Producción Diaria de Queso | B23: 1911 | C23: unidades/día | D23: Bloques de queso empacados al vacío por turno
A24: Reducción Media de Sobrepeso (Giveaway) | B24: 0.013 | C24: kg/unidad | D24: Recuperación de 13 g/bloque al controlar tolerancia a ±1 g con Checkweigher
A25: Queso Recuperado por Día | B25: =B23*B24 -> 24.843 | C25: kg/día | D25: Materia prima ahorrada diariamente por control metrológico
A26: Costo de Materia Prima (Queso Terminado) | B26: 12500 | C26: COP / kg | D26: Costo directo de producción por kilogramo de queso
A27: Operarios Reasignados de Cuarto Frío (8°C) | B27: 2 | C27: operarios | D27: Personal liberado de estiba manual y reasignado a salmuera/calidad
A28: Costo Mensual Consolidado por Operario (MOD) | B28: 2600000 | C28: COP / mes | D28: SMMLV + auxilio transporte + 52% factor prestacional y dotación térmica
A29: Meses Liquidados al Año | B29: 12 | C29: meses/año | D29: Período anual de nómina directa

Sheet 2_CAPEX_Inversion
A1: PRESUPUESTO DETALLADO DE INVERSIÓN INICIAL (CAPEX)
A2: Desglose de Hardware de Paletizado, Instrumentación Metrológica, Comercio Exterior e Ingeniería de Integración
A4: Ítem | B4: Componente / Subsistema | C4: Fabricante y Referencia | D4: Especificaciones Técnicas | E4: Costo (USD) | F4: Costo (COP) | G4: % Participación
A5: A | B5: Hardware de Paletizado y Fuerza
A6: 1.1 | B6: Manipulador Robótico Industrial | C6: Yaskawa Motoman PL80 | D6: 4 ejes, carga máx. 80 kg, alcance 2.061 mm, muñeca IP67 apta para frío. | E6: 39500 | F6: =E6*'1_Parametros_y_Supuestos'!$B$6 -> 126112835 | G6: =F6/$F$33 -> 0.25622767
A7: 1.2 | B7: Gabinete Controlador de Celda | C7: Yaskawa YRC1000 | D7: Controlador compacto con buses de campo PROFINET y Ethernet/IP. | E7: 8000 | F7: =E7*'1_Parametros_y_Supuestos'!$B$6 -> 25541840 | G7: =F7/$F$33 -> 0.051894213
A8: 1.3 | B8: Teach Pendant de Operación | C8: Yaskawa JZRCR-YPP21-1 | D8: Consola táctil ergonómica con cable flexible apantallado de 8 m. | E8: 3200 | F8: =E8*'1_Parametros_y_Supuestos'!$B$6 -> 10216736 | G8: =F8/$F$33 -> 0.020757685
A9: 1.4 | B9: Mazo de Cables Extendidos | C9: Yaskawa Kit 15 m | D9: Potencia y encoders de 15 m para situar el gabinete fuera del cuarto frío. | E9: 1800 | F9: =E9*'1_Parametros_y_Supuestos'!$B$6 -> 5746914 | G9: =F9/$F$33 -> 0.011676198
A10: 1.5 | B10: Gripper (Placa de Vacío) | C10: Schmalz FXP-440-3R36-O10-F | D10: Placa de esponja EPDM con eyectores neumáticos multi-etapa integrados. | E10: 5800 | F10: =E10*'1_Parametros_y_Supuestos'!$B$6 -> 18517834 | G10: =F10/$F$33 -> 0.037623304
A11: 1.6 | B11: Brida de Acople Mecánico | C11: Schmalz FLA-FXP-ISO-9409-1 | D11: Acople normalizado ISO al vástago del eje 4 del manipulador PL80. | E11: 450 | F11: =E11*'1_Parametros_y_Supuestos'!$B$6 -> 1436728.5 | G11: =F11/$F$33 -> 0.0029190495
A12: 1.7 | B12: Compresor de Tornillo Rotativo | C12: Atlas Copco G 7P-10 FF | D12: 7,5 kW (10 HP), 38 CFM @ 10 bar, secador frigorífico integrado (+3°C). | E12: 8200 | F12: =E12*'1_Parametros_y_Supuestos'!$B$6 -> 26180386 | G12: =F12/$F$33 -> 0.053191568
A13: 1.8 | B13: Tanque Pulmón y Filtración | C13: Vertical 500 L + Filtro UD 15+ | D13: Acumulador 11 bar, purga automática y filtración coalescente 0,01 µm. | E13: 2050 | F13: =E13*'1_Parametros_y_Supuestos'!$B$6 -> 6545096.5 | G13: =F13/$F$33 -> 0.013297892
A14: 1.9 | B14: Transportador Infeed Motorizado | C14: Interroll MDR Serie 24V | D14: Rodillos RollerDrive EC5000 (2,5 m), acumulación cero presión y topes Festo. | E14: 6700 | F14: =E14*'1_Parametros_y_Supuestos'!$B$6 -> 21391291 | G14: =F14/$F$33 -> 0.043461403
A15: 1.10 | B15: Seguridad Física y Perimetral | C15: Troax Smart Fix + SICK deTec4 | D15: Cerramiento metálico h=2.050 mm, cortina óptica con muting y enclavamiento Euchner. | E15: 7550 | F15: =E15*'1_Parametros_y_Supuestos'!$B$6 -> 24105112 | G15: =F15/$F$33 -> 0.048975163
A16: 1.11 | B16: Tablero Eléctrico y Pasamuros | C16: Siemens S7-1214FC + Roxtec | D16: PLC Fail-safe, HMI KTP700 7", gabinete Rittal y pasamuros térmico hermético. | E16: 8400 | F16: =E16*'1_Parametros_y_Supuestos'!$B$6 -> 26818932 | G16: =F16/$F$33 -> 0.054488923
B17: Subtotal A - Hardware de Paletizado y Fuerza | E17: =SUM(E6:E16) -> 91650 | F17: =E17*'1_Parametros_y_Supuestos'!$B$6 -> 2.926137e+08 | G17: =F17/$F$33 -> 0.59451307
A18: B | B18: Inspección de Calidad en Línea
A19: 2.1 | B19: Báscula Dinámica (Checkweigher) | C19: Cinta pesadora AISI 304L | D19: Celda digital de pesaje en continuo (±0,5 g), banda de descarte y brazo neumático. | E19: 6500 | F19: =E19*'1_Parametros_y_Supuestos'!$B$6 -> 20752745 | G19: =F19/$F$33 -> 0.042164048
A20: 2.2 | B20: Sistema de Visión Artificial | C20: Cámara matricial IP67 industrial | D20: Domo polarizado, software OCR/OCV para inspección de sellos, lote y fecha. | E20: 7500 | F20: =E20*'1_Parametros_y_Supuestos'!$B$6 -> 23945475 | G20: =F20/$F$33 -> 0.048650824
B21: Subtotal B - Inspección de Calidad en Línea | E21: =SUM(E19:E20) -> 14000 | F21: =E21*'1_Parametros_y_Supuestos'!$B$6 -> 44698220 | G21: =F21/$F$33 -> 0.090814872
A22: C | B22: Comercio Exterior y Aduana
A23: 3.1 | B23: Flete Internacional y Arancel | C23: Nacionalización consolidada | D23: Transporte marítimo/aéreo multimodal, seguros y arancel aduanero DIAN. | E23: 1200 | F23: =E23*'1_Parametros_y_Supuestos'!$B$6 -> 3831276 | G23: =F23/$F$33 -> 0.0077841319
B24: Subtotal C - Comercio Exterior y Aduana | E24: =SUM(E23:E23) -> 1200 | F24: =E24*'1_Parametros_y_Supuestos'!$B$6 -> 3831276 | G24: =F24/$F$33 -> 0.0077841319
A25: D | B25: Servicios de Integración (Nuestra Empresa)
A26: 4.1 | B26: Ingeniería de Detalle y Planos | C26: EPLAN / Simulación cinemática | D26: Ingeniería eléctrica, mecánica 3D, arquitectura de seguridad ISO 10218. | E26: 5500 | F26: =E26*'1_Parametros_y_Supuestos'!$B$6 -> 17560015 | G26: =F26/$F$33 -> 0.035677271
A27: 4.2 | B27: Montaje Electromecánico | C27: Obra civil y mecánica a 8°C | D27: Canalización conduit sanitaria en acero inoxidable AISI 304 y neumática. | E27: 4000 | F27: =E27*'1_Parametros_y_Supuestos'!$B$6 -> 12770920 | G27: =F27/$F$33 -> 0.025947106
A28: 4.3 | B28: Programación y Software | C28: MotoPallet + TIA Portal + Visión | D28: Algoritmos de estibado, parametrización de visión y recetas ISA-88 en HMI. | E28: 5500 | F28: =E28*'1_Parametros_y_Supuestos'!$B$6 -> 17560015 | G28: =F28/$F$33 -> 0.035677271
A29: 4.4 | B29: Puesta en Marcha (FAT / SAT) | C29: Comisionamiento y calibración | D29: Sintonización de báscula dinámica, calibración cinemática y pruebas SAT. | E29: 3500 | F29: =E29*'1_Parametros_y_Supuestos'!$B$6 -> 11174555 | G29: =F29/$F$33 -> 0.022703718
A30: 4.5 | B30: Capacitación Técnica Certificada | C30: Nivel 1 (Operación) / Nivel 2 | D30: Formación de operarios de celda y técnicos de mantenimiento de planta. | E30: 2500 | F30: =E30*'1_Parametros_y_Supuestos'!$B$6 -> 7981825 | G30: =F30/$F$33 -> 0.016216941
A31: 4.6 | B31: Sueldo Ingenieros | C31: Salario para los 6 ingenieros asociados al proyecto | D31: Salario de 3500000 | E31: =F31/'1_Parametros_y_Supuestos'!B6 -> 26309.773 | F31: =3500000*6*4 -> 84000000 | G31: =F31/$F$33 -> 0.17066562
B32: Subtotal D - Servicios de Integración | E32: =SUM(E26:E31) -> 47309.773 | F32: =E32*'1_Parametros_y_Supuestos'!$B$6 -> 1.5104733e+08 | G32: =F32/$F$33 -> 0.30688792
A33: TOTAL | B33: INVERSIÓN INICIAL (I0) - SOLUCIÓN LLAVE EN MANO | C33: Hardware + Calidad + Integración | D33: 82,5% Activos e Instrumentación / 17,5% Ingeniería | E33: =E17+E21+E24+E32 -> 154159.77 | F33: =F17+F21+F24+F32 -> 4.9219053e+08 | G33: =G17+G21+G24+G32 -> 1
B35: RESUMEN EJECUTIVO POR SUBSISTEMA (CAPEX)
B36: Categoría | C36: Subsistema | D36: USD | E36: COP | F36: % Total
B37: A | C37: Hardware de Paletizado y Fuerza | D37: =E17 -> 91650 | E37: =F17 -> 2.926137e+08 | F37: =G17 -> 0.59451307
B38: B | C38: Inspección de Calidad en Línea | D38: =E21 -> 14000 | E38: =F21 -> 44698220 | F38: =G21 -> 0.090814872
B39: C | C39: Comercio Exterior y Aduana | D39: =E24 -> 1200 | E39: =F24 -> 3831276 | F39: =G24 -> 0.0077841319 | G39: =F39+F38+F37 -> 0.69311208
B40: D | C40: Servicios de Integración | D40: =E32 -> 47309.773 | E40: =F32 -> 1.5104733e+08 | F40: =G32 -> 0.30688792

Sheet 3_OPEX_y_Beneficios
A1: COSTOS OPERATIVOS ANUALES (OPEX), BENEFICIOS Y MARGEN EBITDA
A2: Cálculo paramétrico de gastos de operación continua (2.496 h/año) y ahorros proyectados en planta
A4: 1. DESGLOSE DE COSTOS OPERATIVOS ANUALES (OPEX)
A5: Ítem | B5: Rubro Operativo (OPEX) | C5: Base de Cálculo / Frecuencia | D5: Criterio Técnico y Operativo | E5: Costo Anual (COP) | F5: % OPEX
A6: 3.1 | B6: Consumo de Energía Eléctrica | C6: 16.473,6 kWh/año @ $850/kWh | D6: Potencia media 6,6 kW (Robot 1,8 kW + Compresor 3,2 kW + Rodillos 0,8 kW + Calidad 0,8 kW) x 2.496 h/año | E6: ='1_Parametros_y_Supuestos'!B15*'1_Parametros_y_Supuestos'!B20*'1_Parametros_y_Supuestos'!B21 -> 9335040 | F6: =E6/$E$12 -> 0.36133252
A7: 3.2 | B7: Consumibles de Vacío y Desgaste Mecánico | C7: Semestral (2 recambios/año) | D7: Repuesto de esponja EPDM Schmalz por desgaste mecánico y humedad en cuarto frío | E7: 2400000 | F7: =E7/$E$12 -> 0.092897089
A8: 3.3 | B8: Mantenimiento del Sistema de Compresión | C8: Anual preventivo | D8: Kit preventivo Atlas Copco (aceite sintético, elemento separador, filtros de aire y purgas) | E8: 3600000 | F8: =E8/$E$12 -> 0.13934563
A9: 3.4 | B9: Mantenimiento Preventivo del Robot | C9: Anual certificado | D9: Engrase de reductores de 4 ejes (grasa para frío), ajuste cinemático y baterías de encoders | E9: 2500000 | F9: =E9/$E$12 -> 0.096767801
A10: 3.5 | B10: Calibración y Certificación Metrológica | C10: Semestral certificada | D10: Calibración con masas patrón certificadas, reemplazo de luminarias y limpieza óptica | E10: 3500000 | F10: =E10/$E$12 -> 0.13547492
A11: 3.6 | B11: Póliza de Soporte Técnico y Licenciamiento | C11: Semestral programado | D11: Soporte por firma integradora, optimización de trayectorias, respaldo de recetas ISA-88 y soporte remoto | E11: 4500000 | F11: =E11/$E$12 -> 0.17418204
A12: TOTAL | B12: OPEX TOTAL ANUAL PROYECTADO | C12: Operación 312 días/año | D12: Representa el 11,58% de los ahorros brutos anuales generados | E12: =SUM(E6:E11) -> 25835040 | F12: =SUM(F6:F11) -> 1
A15: 2. BENEFICIOS Y AHORROS ANUALES ESTIMADOS (INGRESOS INCREMENTALES / AHORROS)
A16: Ítem | B16: Fuente de Ahorro / Beneficio Operativo | C16: Parámetro de Impacto | D16: Justificación Técnica y Financiera | E16: Ahorro Anual (COP) | F16: % Ahorro
A17: 4.1 | B17: Mitigación de Sobrepeso (Giveaway - Báscula Dinámica) | C17: 30 kg/día x $12.500/kg x 312 días | D17: Ajuste de cabezales a ±1 g recuperando 13 g/unidad en 1911 bloques/día | E17: ='1_Parametros_y_Supuestos'!B25*'1_Parametros_y_Supuestos'!B26*'1_Parametros_y_Supuestos'!B13 -> 64591800 | F17: =E17/$E$22 -> 0.30613417
A18: 4.2 | B18: Supresión de Pérdidas por Fugas de Vacío y Marcaje (Visión) | C18: Inspección 100% termoformados | D18: Detección de microarrugas en sello, grasa atrapada y defectos de lote/fecha (OCR/OCV) | E18: 24000000 | F18: =E18/$E$22 -> 0.1137485
A19: 4.3 | B19: Optimización de Mano de Obra Directa (MOD) en Frío | C19: 2 operarios x $2.600.000/mes x 12 | D19: Ahorro de salarios de 2 operarios de estiba en cuarto frío | E19: ='1_Parametros_y_Supuestos'!B27*'1_Parametros_y_Supuestos'!B28*'1_Parametros_y_Supuestos'!B29 -> 62400000 | F19: =E19/$E$22 -> 0.29574609
A20: 4.4 | B20: Reducción de Mermas por Desplome y Aplastamiento | C20: Mosaico cruzado MotoPallet | D20: Eliminación de daño mecánico en cajas basales de 15 kg gracias al agarre plano Schmalz | E20: 45000000 | F20: =E20/$E$22 -> 0.21327843
A21: 4.5 | B21: Disminución de Costos Ocultos por Incapacidades (ARL) | C21: Ergonomía e higiene postural | D21: Erradicación de levantamiento repetitivo en frío, reduciendo ausentismo y riesgo osteomuscular | E21: 15000000 | F21: =E21/$E$22 -> 0.07109281
A22: TOTAL | B22: AHORRO BRUTO ANUAL CONSOLIDADO | C22: 5 pilares de eficiencia | D22: Impulsado en 30,61% por recuperación metrológica (giveaway) y 29,57% por MOD | E22: =SUM(E17:E21) -> 210991800 | F22: =SUM(F17:F21) -> 1
A25: 3. CONSOLIDACIÓN DE MÁRGENES OPERATIVOS ANUALES (EBITDA DE LA CELDA)
A26: (+) Ahorro Bruto Anual | E26: =E22 -> 210991800 | F26: =E26/$E$26 -> 1
A27: (-) Costos Operativos Anuales (OPEX) | E27: =-E12 -> -25835040 | F27: =E12/$E$26 -> 0.12244571
A28: (=) MARGEN OPERATIVO BRUTO (EBITDA ANUAL DE LA CELDA) | E28: =E26+E27 -> 185156760 | F28: =E28/$E$26 -> 0.87755429

Sheet 4_Flujo_de_Caja_y_VPN
A1: PROYECCIÓN DEL FLUJO DE CAJA LIBRE OPERATIVO (FCLO A 5 AÑOS) Y ANÁLISIS DE PAYBACK
A2: Estado de resultados proyectado, escudo fiscal por depreciación lineal, flujos descontados al 13,50% E.A. y recuperación
A4: PREMISAS FINANCIERAS Y TRIBUTARIAS APLICADAS AL FLUJO
A5: Inversión Inicial (I0): | B5: ='2_CAPEX_Inversion'!F33 -> 4.9219053e+08 | D5: Depreciación Anual (5 años): | E5: ='2_CAPEX_Inversion'!F33/'1_Parametros_y_Supuestos'!B10 -> 98438106
A6: Impuesto de Renta: | B6: ='1_Parametros_y_Supuestos'!B9 -> 0.35 | D6: Valor de Salvamento (Año 5): | E6: ='1_Parametros_y_Supuestos'!B11 -> 40000000
A7: Tasa de Descuento (TIO): | B7: ='1_Parametros_y_Supuestos'!B8 -> 0.135 | D7: Horizonte del Proyecto: | E7: ='1_Parametros_y_Supuestos'!B7 -> 5
A9: Rubro Financiero (COP) | B9: Año 0 | C9: Año 1 | D9: Año 2 | E9: Año 3 | F9: Año 4 | G9: Año 5 | H9: Total Acumulado (1-5)
A10: Inversión Inicial (I0) | B10: =-'2_CAPEX_Inversion'!F33 -> -4.9219053e+08 | C10: 0 | D10: 0 | E10: 0 | F10: 0 | G10: 0 | H10: =B10 -> -4.9219053e+08
A11: (+) Ahorros Brutos Operativos | B11: 0 | C11: ='3_OPEX_y_Beneficios'!$E$22 -> 210991800 | D11: ='3_OPEX_y_Beneficios'!$E$22 -> 210991800 | E11: ='3_OPEX_y_Beneficios'!$E$22 -> 210991800 | F11: ='3_OPEX_y_Beneficios'!$E$22 -> 210991800 | G11: ='3_OPEX_y_Beneficios'!$E$22 -> 210991800 | H11: =SUM(C11:G11) -> 1054959000
A12: (-) Costos Operativos (OPEX) | B12: 0 | C12: =-'3_OPEX_y_Beneficios'!$E$12 -> -25835040 | D12: =-'3_OPEX_y_Beneficios'!$E$12 -> -25835040 | E12: =-'3_OPEX_y_Beneficios'!$E$12 -> -25835040 | F12: =-'3_OPEX_y_Beneficios'!$E$12 -> -25835040 | G12: =-'3_OPEX_y_Beneficios'!$E$12 -> -25835040 | H12: =SUM(C12:G12) -> -129175200
A13: (=) EBITDA (Margen Operativo Bruto) | B13: 0 | C13: =C11+C12 -> 185156760 | D13: =D11+D12 -> 185156760 | E13: =E11+E12 -> 185156760 | F13: =F11+F12 -> 185156760 | G13: =G11+G12 -> 185156760 | H13: =SUM(C13:G13) -> 925783800
A14: (-) Depreciación Fiscal Línea Recta | B14: 0 | C14: =-$E$5 -> -98438106 | D14: =-$E$5 -> -98438106 | E14: =-$E$5 -> -98438106 | F14: =-$E$5 -> -98438106 | G14: =-$E$5 -> -98438106 | H14: =SUM(C14:G14) -> -4.9219053e+08
A15: (=) Utilidad Antes de Impuestos (EBIT) | B15: 0 | C15: =C13+C14 -> 86718654 | D15: =D13+D14 -> 86718654 | E15: =E13+E14 -> 86718654 | F15: =F13+F14 -> 86718654 | G15: =G13+G14 -> 86718654 | H15: =SUM(C15:G15) -> 4.3359327e+08
A16: (-) Impuesto sobre la Renta (35%) | B16: 0 | C16: =-C15*$B$6 -> -30351529 | D16: =-D15*$B$6 -> -30351529 | E16: =-E15*$B$6 -> -30351529 | F16: =-F15*$B$6 -> -30351529 | G16: =-G15*$B$6 -> -30351529 | H16: =SUM(C16:G16) -> -1.5175764e+08
A17: (=) Utilidad Neta del Proyecto | B17: 0 | C17: =C15+C16 -> 56367125 | D17: =D15+D16 -> 56367125 | E17: =E15+E16 -> 56367125 | F17: =F15+F16 -> 56367125 | G17: =G15+G16 -> 56367125 | H17: =SUM(C17:G17) -> 2.8183563e+08
A18: (+) Reversión de Depreciación Fiscal | B18: 0 | C18: =-C14 -> 98438106 | D18: =-D14 -> 98438106 | E18: =-E14 -> 98438106 | F18: =-F14 -> 98438106 | G18: =-G14 -> 98438106 | H18: =SUM(C18:G18) -> 4.9219053e+08
A19: (+) Valor de Salvamento (Vs) | B19: 0 | C19: 0 | D19: 0 | E19: 0 | F19: 0 | G19: =$E$6 -> 40000000 | H19: =SUM(C19:G19) -> 40000000
A20: Flujo de Caja Libre Operativo (FCLO) | B20: =B10 -> -4.9219053e+08 | C20: =C17+C18+C19 -> 1.5480523e+08 | D20: =D17+D18+D19 -> 1.5480523e+08 | E20: =E17+E18+E19 -> 1.5480523e+08 | F20: =F17+F18+F19 -> 1.5480523e+08 | G20: =G17+G18+G19 -> 1.9480523e+08 | H20: =SUM(C20:G20) -> 8.1402616e+08
A23: ANÁLISIS DE DESCUENTO DE FLUJOS (TIO = 13,50% E.A.) Y RECUPERACIÓN DE CAPITAL (PAYBACK)
A24: Período (Año t) | B24: 0 | C24: 1 | D24: 2 | E24: 3 | F24: 4 | G24: 5 | H24: N/A
A25: Factor de Descuento [1 / (1 + TIO)^t] | B25: =1/(1+$B$7)^B24 -> 1 | C25: =1/(1+$B$7)^C24 -> 0.88105727 | D25: =1/(1+$B$7)^D24 -> 0.77626191 | E25: =1/(1+$B$7)^E24 -> 0.6839312 | F25: =1/(1+$B$7)^F24 -> 0.60258255 | G25: =1/(1+$B$7)^G24 -> 0.53090974 | H25: N/A
A26: Flujo de Caja Nominal Acumulado (Payback Simple) | B26: =B20 -> -4.9219053e+08 | C26: =B26+C20 -> -3.373853e+08 | D26: =C26+D20 -> -1.8258007e+08 | E26: =D26+E20 -> -27774837 | F26: =E26+F20 -> 1.2703039e+08 | G26: =F26+G20 -> 3.2183563e+08 | H26: =G26 -> 3.2183563e+08
A27: Flujo de Caja Descontado [FCLO / (1 + TIO)^t] | B27: =B20*B25 -> -4.9219053e+08 | C27: =C20*C25 -> 1.3639227e+08 | D27: =D20*D25 -> 1.201694e+08 | E27: =E20*E25 -> 1.0587613e+08 | F27: =F20*F25 -> 93282932 | G27: =G20*G25 -> 1.0342399e+08 | H27: =SUM(C27:G27) -> 5.5914473e+08
A28: Flujo Descontado Acumulado (Payback Descontado) | B28: =B27 -> -4.9219053e+08 | C28: =B28+C27 -> -3.5579826e+08 | D28: =C28+D27 -> -2.3562885e+08 | E28: =D28+E27 -> -1.2975272e+08 | F28: =E28+F27 -> -36469793 | G28: =F28+G27 -> 66954202 | H28: =G28 -> 66954202

Sheet 5_Dashboard_Ejecutivo
A1: MATRIZ CONSOLIDADA DE DECISIÓN FINANCIERA Y DASHBOARD EJECUTIVO
A2: Evaluación de Indicadores de Rentabilidad (VPN, TIR, Payback, ROI) | Celda Robotizada 3 en 1 (8°C)
A4: 1. MATRIZ CONSOLIDADA DE INDICADORES Y DICTAMEN DE VIABILIDAD FINANCIERA
A5: Parámetro / Indicador Financiero | B5: Valor Proyectado | C5: Unidad | D5: Criterio de Decisión | E5: Dictamen Financiero | F5: Estado
A6: Inversión Inicial Total (CAPEX - I0) | B6: ='2_CAPEX_Inversion'!F33 -> 4.9219053e+08 | C6: COP | D6: Presupuesto integral | E6: 69,31% Activos y Calidad / 30,69% Integración | F6: APROBADO
A7: Inversión Inicial en Moneda Extranjera | B7: ='2_CAPEX_Inversion'!E33 -> 154159.77 | C7: USD | D7: Tasa: $4.124,50 COP/USD | E7: Equipamiento importado y nacionalizado | F7: APROBADO
A8: Costo Operativo Anual (OPEX Celda) | B8: ='3_OPEX_y_Beneficios'!E12 -> 25835040 | C8: COP/año | D8: Sostenibilidad de planta | E8: Representa solo el 12,24% del ahorro bruto anual | F8: ÓPTIMO
A9: Ahorro Bruto Anual Estimado | B9: ='3_OPEX_y_Beneficios'!E22 -> 210991800 | C9: COP/año | D9: Alto impacto operativo | E9: Impulsado en 30,61% por giveaway y 29,57% por nómina | F9: ALTO IMPACTO
A10: Margen Operativo Bruto (EBITDA Anual) | B10: ='3_OPEX_y_Beneficios'!E28 -> 185156760 | C10: COP/año | D10: Margen > 80% sobre ahorro | E10: Generación operativa neta del 87,66% | F10: ROBUSTO
A11: Flujo de Caja Libre Operativo (Años 1 a 4) | B11: ='4_Flujo_de_Caja_y_VPN'!C20 -> 1.5480523e+08 | C11: COP/año | D11: Flujo neto post-impuestos | E11: Incluye escudo fiscal por depreciación lineal | F11: POSITIVO
A12: Flujo de Caja Libre Operativo (Año 5 + Salvamento) | B12: ='4_Flujo_de_Caja_y_VPN'!G20 -> 1.9480523e+08 | C12: COP | D12: Liquidación residual | E12: Incluye recuperación de $40.000.000 de salvamento | F12: POSITIVO
A13: Tasa de Interés de Oportunidad (TIO / WACC) | B13: ='1_Parametros_y_Supuestos'!B8 -> 0.135 | C13: % E.A. | D13: Referencia sectorial | E13: Costo de oportunidad ajustado al perfil de riesgo | F13: BASE
A14: Suma de Flujos de Caja Descontados (Años 1-5) | B14: ='4_Flujo_de_Caja_y_VPN'!H27 -> 5.5914473e+08 | C14: COP | D14: VP de flujos > I0 | E14: Valor presente bruto generado por la operación | F14: SUPERÁVIT
A15: Valor Presente Neto (VPN) | B15: =NPV('1_Parametros_y_Supuestos'!B8,'4_Flujo_de_Caja_y_VPN'!C20:G20)+'4_Flujo_de_Caja_y_VPN'!B20 -> 66954202 | C15: COP | D15: VPN > $0 COP | E15: Viable: Agrega valor neto al patrimonio de la empresa | F15: VIABLE
A16: Tasa Interna de Retorno (TIR) | B16: =IRR('4_Flujo_de_Caja_y_VPN'!B20:G20) -> 0.18815156 | C16: % E.A. | D16: TIR > TIO (13,50%) | E16: Rentable: Rentabilidad robusta con +5,32% sobre la TIO | F16: RENTABLE
A17: Margen de Seguridad Financiera (Spread TIR - TIO) | B17: =B16-B13 -> 0.053151559 | C17: % | D17: Spread > 5,00% | E17: Tolera sobrecostos o alzas de tasas de hasta 5,32 pp | F17: HOLGADO
A18: Período de Recuperación Nominal (Payback Simple) | B18: =-'4_Flujo_de_Caja_y_VPN'!B20/'4_Flujo_de_Caja_y_VPN'!C20 -> 3.1794179 | C18: Años | D18: < 3,5 años | E18: Recuperación nominal en 3 años y 2 meses | F18: CUMPLE
A19: Período de Recuperación Real (Payback Descontado) | B19: =3+(-'4_Flujo_de_Caja_y_VPN'!E28/'4_Flujo_de_Caja_y_VPN'!F27) -> 4.3909589 | C19: Años | D19: < 4,5 años | E19: Recuperación real en 4 años y 4 meses (dentro de vida fiscal) | F19: CUMPLE
A20: Retorno sobre la Inversión Anual (ROI Anual) | B20: ='4_Flujo_de_Caja_y_VPN'!C20/(-'4_Flujo_de_Caja_y_VPN'!B20) -> 0.31452298 | C20: % / año | D20: > 25,0% anual | E20: Retorno operativo anual medio sobre capital invertido | F20: VIABLE
A21: Retorno sobre la Inversión Acumulado (ROI 5 Años) | B21: =('4_Flujo_de_Caja_y_VPN'!H20+'4_Flujo_de_Caja_y_VPN'!B20)/(-'4_Flujo_de_Caja_y_VPN'!B20) -> 0.65388423 | C21: % (5 años) | D21: > 50,0% acumulado | E21: El proyecto retorna casi la totalidad de su capital neto | F21: EXCELENTE
